pygqlc/GraphQLClient.py
pygqlc/MutationBatch.py
pygqlc/MutationParser.py
pygqlc/QueryBatch.py
pygqlc/QueryParser.py
pygqlc/SubscriptionParser.py
pygqlc/__init__.py
pygqlc/__main__.py
pygqlc/__version__.py
pygqlc/helper_modules/Singleton.py
pygqlc/helper_modules/__init__.py
pygqlc/logging.py
pygqlc-3.5.5.dist-info/LICENCE
pygqlc-3.5.5.dist-info/METADATA
pygqlc-3.5.5.dist-info/WHEEL
pygqlc-3.5.5.dist-info/RECORD
