Metadata-Version: 2.1
Name: pygqlc
Version: 3.5.5
Summary: Python client for graphql APIs
Author: Baruc Almaguer
Author-email: baruc.almaguer@gmail.com
Requires-Python: >=3.11,<4.0
Classifier: Programming Language :: Python :: 3
Classifier: Programming Language :: Python :: 3.11
Classifier: Programming Language :: Python :: 3.12
Provides-Extra: valiotlogging
Requires-Dist: certifi (>=2025.1.31,<2026.0.0)
Requires-Dist: httpx[http2] (>=0.28.1,<0.29.0)
Requires-Dist: orjson (>=3.10.0,<4.0.0)
Requires-Dist: pydash (>=8.0,<9.0)
Requires-Dist: tenacity (>=9.0,<10.0)
Requires-Dist: valiotlogging (>=0.1.0,<2.0) ; extra == "valiotlogging"
Requires-Dist: websocket-client (>=1.8,<2.0)
